flask_avatars/__init__.py
flask_avatars/identicon.py
flask_avatars/static/default/default_l.jpg
flask_avatars/static/default/default_m.jpg
flask_avatars/static/default/default_s.jpg
flask_avatars/static/jcrop/MIT-LICENSE.txt
flask_avatars/static/jcrop/css/Jcrop.gif
flask_avatars/static/jcrop/css/jquery.Jcrop.css
flask_avatars/static/jcrop/css/jquery.Jcrop.min.css
flask_avatars/static/jcrop/js/jquery.Jcrop.js
flask_avatars/static/jcrop/js/jquery.Jcrop.min.js
flask_avatars/static/jcrop/js/jquery.color.js
flask_avatars/static/jcrop/js/jquery.min.js
Flask_Avatars-0.2.3.dist-info/LICENSE
Flask_Avatars-0.2.3.dist-info/METADATA
Flask_Avatars-0.2.3.dist-info/WHEEL
Flask_Avatars-0.2.3.dist-info/top_level.txt
Flask_Avatars-0.2.3.dist-info/RECORD
